rdddy/__init__.py
rdddy/api.py
rdddy/app.py
rdddy/cli.py
rdddy-0.0.0.dist-info/METADATA
rdddy-0.0.0.dist-info/WHEEL
rdddy-0.0.0.dist-info/entry_points.txt
rdddy-0.0.0.dist-info/RECORD
