Metadata-Version: 2.1
Name: rdddy
Version: 0.0.0
Summary: Reactive DDD framework with DSPy
Home-page: https://github.com/chatmangpt/rdddy
Author: Sean Chatman
Author-email: info@chatmangpt.com
Requires-Python: >=3.10,<4.0
Classifier: Programming Language :: Python :: 3
Classifier: Programming Language :: Python :: 3.10
Classifier: Programming Language :: Python :: 3.11
Classifier: Programming Language :: Python :: 3.12
Requires-Dist: coloredlogs (>=15.0.1)
Requires-Dist: dspy-ai (>=2.1.1,<3.0.0)
Requires-Dist: fastapi[all] (>=0.92.0)
Requires-Dist: gunicorn (>=20.1.0)
Requires-Dist: jinja2 (>=3.1.3,<4.0.0)
Requires-Dist: poethepoet (>=0.20.0)
Requires-Dist: pydantic (>=1.10.7)
Requires-Dist: streamlit (>=1.19.0)
Requires-Dist: typer[all] (>=0.9.0)
Requires-Dist: uvicorn[standard] (>=0.20.0)
Project-URL: Repository, https://github.com/chatmangpt/rdddy
